{
  "author_id": 119,
  "author_meta": "ابن أَبي حاتِم (٢٤٠ - ٣٢٧ هـ = ٨٥٤ - ٩٣٨ م)\nعبد الرحمن بن محمد أبي حاتم ابن إدريس بن المنذر التميمي الحنظليّ الرازيّ، أبو محمد\nحافظ للحديث، من كبارهم.\nكان منزله في درب حنظلة بالريّ، وإليهما نسبته.\nله تصانيف، منها:\n(الجرح والتعديل - ط) ثمانية مجلدات منه\n(التفسير) عدة مجلدات، منها جزآن مخطوطان [طُبِع]\n(الرد على الجهمية) كبير\n(علل الحديث - ط) جزآن\n(المسند) كبير\n(الكنى)\n(الفوائد الكبرى)\n(المراسيل - ط)\n(تقدمة المعرفة بكتاب الجرح والتعديل - خ) في دار الكتب (٩٠ مصطلح)\n(زهد الثمانية من التابعين - خ) في الظاهرية.\n(آداب الشافعيّ ومناقبه - ط)\n(بيان خطأ أبي عبد الله محمد بن إسماعيل البخاري في تاريخه - ط) (١).\n_________\n(١) تذكرة الحفاظ ٣: ٤٦ وفوات الوفيات ١: ٢٦٠ وطبقات الحنابلة ٢: ٥٥ والمقصد الأرشد - خ. وفيه: وفاته سنة ٣٢٩ هـ ومخطوطات الظاهرية ٢٧٧ والفهرس التمهيدي ٣٧٧ ومعجم المطبوعات ٢٨ والخزانة التيمورية ٢: ٣٠٤ والمخطوطات المصورة، التاريخ ٢ القسم الرابع ١١٨.\nنقلا عن: «الأعلام» للزركلي [مع إضافة بين معقوفين]",
  "books": [
    {
      "text_id": 1076,
      "title": "بيان خطا البخاري في تاريخه"
    },
    {
      "text_id": 1350,
      "title": "العلل لابن أبي حاتم ت الحميد"
    },
    {
      "text_id": 1485,
      "title": "آداب الشافعي ومناقبه - ط العلمية"
    },
    {
      "text_id": 2170,
      "title": "الجرح والتعديل لابن أبي حاتم"
    },
    {
      "text_id": 6046,
      "title": "المراسيل لابن أبي حاتم"
    },
    {
      "text_id": 8658,
      "title": "تفسير ابن أبي حاتم"
    }
  ]
}