{
  "author_id": 1207,
  "author_meta": "المنذري (٥٨١ - ٦٥٦ هـ = ١١٨٥ - ١٢٥٨ م)\nعبد العظيم بن عبد القوي بن عبد الله، أبو محمد، زكي الدين المنذري\nعالم بالحديث والعربية، من الحفاظ المؤرخين. مولده ووفاته بمصر.\nأصله من الشام، تولى مشيخة دار الحديث الكاملية (بالقاهرة) وانقطع بها نحو عشرين سنة، عاكفا على التصنيف والتخريج والإفادة والتحديث\nله:\n«الترغيب والترهيب - ط»\n«التكملة لوفيات النقلة - ط» أجزاء منه،\n«أربعون حديثا - ط» رسالة،\n«شرح التنبيه»\n«مختصر صحيح مسلم - ط» في الهند مع شرحه لصديق حسن خان،\n«مختصر سنن أبي داود - ط»\nوصنف محقق كتابه «التكملة» بشار عواد معروف، كتاب «المنذري وكتابه التكملة لوفيات النقلة - ط»\nنقلا عن: «الأعلام» للزركلي",
  "books": [
    {
      "text_id": 13223,
      "title": "الترغيب والترهيب للمنذري - ت عمارة"
    },
    {
      "text_id": 159,
      "title": "التكملة لوفيات النقلة"
    },
    {
      "text_id": 17616,
      "title": "مختصر صحيح مسلم للمنذري ت الألباني"
    },
    {
      "text_id": 17794,
      "title": "جزء فيه ذكر حال عكرمة مولى عبد الله بن عباس وما قيل فيه"
    },
    {
      "text_id": 20944,
      "title": "مختصر سنن أبي داود للمنذري ت حلاق"
    },
    {
      "text_id": 29464,
      "title": "جزء حديث المتبايعين بالخيار"
    },
    {
      "text_id": 6847,
      "title": "الترغيب والترهيب للمنذري - ط العلمية"
    },
    {
      "text_id": 9863,
      "title": "جواب الحافظ المنذري عن أسئلة في الجرح والتعديل"
    }
  ]
}