{
  "author_id": 1286,
  "author_meta": "أبو بكر المراغي (٧٢٧ - ٨١٦ هـ = ١٣٢٧ - ١٤١٤ م)\nأبو بكر بن الحسين بن عمر، القرشي العبشمي الأموي العثماني، زين الدين، وكنيته أبو محمد ويقال اسمه (عبد الله) والمشهور (أبو بكر) المصري الشافعي المراغي: مؤرخ ولد بالقاهرة وقرأ واشتهر، وتحول إلى المدينة فاستوطنها نحو ٥٠ سنة، وولي قضاءها وخطابتها وإمامتها سنة ٨٠٩ وصرف بعد سنة ونصف، وأقام بمكة سنتين، ومات بالمدينة. له (تحقيق النصرة بتلخيص معالم دار الهجرة - ط) في تاريخ المدينة، أنجزه سنة ٧٦٦ و (روائح الزهر) اختصر به الزهر الباسم، في السيرة النبوية، لمغلطاي، و (الوافي) أكمل به شرح شيخه الأسنوي للمنهاج..وغير ذلك\nنقلا عن : الأعلام للزركلي",
  "books": [
    {
      "text_id": 26731,
      "title": "مشيخة أبي بكر المراغي"
    },
    {
      "text_id": 9375,
      "title": "الأربعون من عوالي المجيزين"
    }
  ]
}