{
  "author_id": 1472,
  "author_meta": "الأُشْمُوني (٨٣٨ - نحو ٩٠٠ هـ = ١٤٣٥ - نحو ١٤٩٥ م)\nعلي بن محمد بن عيسى، أبو الحسن، نور الدين الأشموني: نحوي، من فقهاء الشافعية.\nأصله من أشمون (بمصر) ومولده بالقاهرة. ولى القضاة بدمياط. وصنف «شرح ألفية ابن مالك - ط» في النحو، و «نظم المنهاج» في الفقه، و «شرحه» و «نظم جمع الجوامع» و «نظم إيساغوجي» في المنطق. قال السخاوي: راج أمره ورجح على الجلال بن الأسيوطي، مع اشتراكهما في الحمق! غير أن ذلك أرجح\nنقلا عن: الأعلام للزركلي",
  "books": [
    {
      "text_id": 11742,
      "title": "شرح الأشمونى لألفية ابن مالك"
    }
  ]
}