{
  "author_id": 1555,
  "author_meta": "الدكتور عبد الوهاب إبراهيم أبو سليمان\n- ولد في مكة المكرمة عام ١٣٥٦ هـ، ونشأ بها، وتلقى تعليمه العام في رحابها.\n- تتلمذ على علماء الحرم المكي الشريف، وبخاصة العلامة فضيلة الشيخ حسن بن محمد المشاط.\n- حصل على الدكتوراه من جامعة لندن عام ١٣٩٠ هـ/١٩٧٠ م، وعلى دبلوم في القانون من كلية مدينة لندن للدراسات القانونية.\n- رقي إلى درجة أستاذ في الفقه وأصوله عام ١٤٠٣ هـ، وعمل عميداً لكلية الشريعة بجامعة أم القرى\n- أشرف على الكثير من الرسائل العلمية لدرجة الماجستير، والدكتوراه.\n- عين عضواً في الكثير من المجالس العلمية، والأكاديمية بجامعة أم القرى، وغيرها، وشارك في الكثير من المؤتمرات العلمية.\n- عضو في مجلس هيئة كبار العلماء، ومجمع الفقه الإسلامي التابع لمنظمة المؤتمر الإسلامي، وجائزة الأمير نايف العالمية للسنة النبوية، وغيرها من المؤسسات العلمية داخل المملكة وخارجها.\n- استضافته بعض الجامعات أستاذاً زائراً: جامعة هارفارد، جامعة نورث كارولاينا بأمريكا، الجامعة الإسلامية العالمية بماليزيا، جامعة الشيخ زايد بدولة الإمارات العربية المتحدة، كلية الدراسات الإسلامية بدبي، جامعة مفيد بقم بالجمهورية الإسلامية الإيرانية.\n- له مؤلفات وبحوث، ومقالات منشورة: في الفقه، وأصوله، ومناهج البحث وتاريخ مكة المكرمة الحديث.\n[تُوفي ليلة الاثنين ٢٦ رمضان ١٤٤٤ هـ الموافق ١٧ إبريل ٢٠٢٣ م]",
  "books": [
    {
      "text_id": 11173,
      "title": "خصائص التفكير الفقهي عند الشيخ محمد بن عبد الوهاب (مطبوع ضمن بحوث ندوة دعوة الشيخ محمد بن عبد الوهاب، الجزء الأول)"
    },
    {
      "text_id": 11312,
      "title": "عناية المسلمين بالوقف خدمة للقرآن الكريم"
    },
    {
      "text_id": 8350,
      "title": "كتابة البحث العلمي صياغة جديدة"
    }
  ]
}