{
  "author_id": 1653,
  "author_meta": "المَحَلِّي (٠٠٠ - ١١٧٠ هـ = ٠٠٠ - ١٧٥٧ م)\nحسين بن محمد المحلي: فقيه شافعيّ مصري. له (كشف اللثام عن أسئلة الأنام - خ) و (الكشف التام عن إرث ذوي الأرحام - ط) في المواريث، و (كشف الأستار عن مسألة الإقرار - خ) رسالة في المواريث، و (منتهى الإيرادات لجدول المناسخات - خ) شرح به جدول ابن الهائم، و (فتح رب البرية على متن السخاوية - ط) حساب، و (مزيد النعمة لجمع أقوال الأئمة - خ) [ثم طُبع].\nنقلا عن : الأعلام للزركلي",
  "books": [
    {
      "text_id": 11577,
      "title": "مزيد النعمة لجمع أقوال الأئمة"
    }
  ]
}