{
  "author_id": 184,
  "author_meta": "ابن رجب الحنبلي (٧٣٦ - ٧٩٥ هـ، ١٣٣٦ - ١٣٩٣ م).\nزين الدين عبد الرحمن بن أحمد بن رجب بن الحسن، السَلامي، البغدادي، ثم الدمشقي، الحنبلي، الواعظ. الإمام الحافظ، المحدّث، الفقيه، ولد في بغداد وسمع من أبي الفتح الميدومي.\nله مصنفات عديدة، منها:\nشرح الترمذي\nشرح علل الترمذي\nطبقات الحنابلة\nفتح الباري شرح صحيح البخاري لم يتمه\nجامع العلوم والحكم شرح خمسين حديثًا من جوامع الكلم؛\nالتوحيد\nوغيرها.\nنشأ وتوفي بدمشق.\nنقلا عن\nالموسوعة العربية العالمية http://www.mawsoah.net",
  "books": [
    {
      "text_id": 10443,
      "title": "جامع العلوم والحكم - ت أبي النور"
    },
    {
      "text_id": 10463,
      "title": "تفسير ابن رجب الحنبلي"
    },
    {
      "text_id": 1053,
      "title": "ذيل طبقات الحنابلة - لابن رجب - ت الفقي"
    },
    {
      "text_id": 10782,
      "title": "كشف الكربة في وصف أهل الغربة"
    },
    {
      "text_id": 10900,
      "title": "أهوال القبور وأحوال أهلها إلى النشور"
    },
    {
      "text_id": 10910,
      "title": "القاعدة الذهبية لا ضرر ولا ضرار"
    },
    {
      "text_id": 11363,
      "title": "لطائف المعارف فيما لمواسم العام من الوظائف - ط ابن حزم"
    },
    {
      "text_id": 1144,
      "title": "لطائف المعارف فيما لمواسم العام من الوظائف - ت عوض الله"
    },
    {
      "text_id": 1151,
      "title": "لطائف المعارف فيما لمواسم العام من الوظائف - ت عامر"
    },
    {
      "text_id": 1152,
      "title": "لطائف المعارف فيما لمواسم العام من الوظائف - ت السواس"
    },
    {
      "text_id": 132,
      "title": "بيان فضل علم السلف على علم الخلف"
    },
    {
      "text_id": 137,
      "title": "فتح الباري لابن رجب"
    },
    {
      "text_id": 151109,
      "title": "ورثة الأنبياء شرح حديث أبي الدرداء"
    },
    {
      "text_id": 151110,
      "title": "شرح حديث «ما ذئبان جائعان»"
    },
    {
      "text_id": 151111,
      "title": "شرح حديث «لبيك اللهم لبيك»"
    },
    {
      "text_id": 151112,
      "title": "شرح حديث عمار بن ياسر - رضي الله عنه -"
    },
    {
      "text_id": 151113,
      "title": "شرح حديث «مثل الإسلام»"
    },
    {
      "text_id": 151114,
      "title": "غاية النفع في شرح حديث «تمثيل المؤمن بخامة الزرع»"
    },
    {
      "text_id": 151115,
      "title": "الحكم الجديرة بالإذاعة - ضمن مجموع رسائل ابن رجب"
    },
    {
      "text_id": 151116,
      "title": "ذم قسوة القلب"
    },
    {
      "text_id": 151117,
      "title": "ذم الخمر"
    },
    {
      "text_id": 151118,
      "title": "الذل والانكسار للعزيز الجبار"
    },
    {
      "text_id": 151119,
      "title": "كشف الكربة في وصف حال أهل الغربة"
    },
    {
      "text_id": 151120,
      "title": "جزء من الكلام على حديث شداد بن أوس «إذا كنز الناس الذهب والفضة»"
    },
    {
      "text_id": 151121,
      "title": "البشارة العظمى للمؤمن بأن حظه من النار الحمى"
    },
    {
      "text_id": 151122,
      "title": "تسلية نفوس النساء والرجال عند فقد الأطفال"
    },
    {
      "text_id": 151123,
      "title": "الفرق بين النصيحة والتعيير"
    },
    {
      "text_id": 151124,
      "title": "جزء فيه الكلام على حديث يتبع الميت ثلاث"
    },
    {
      "text_id": 151125,
      "title": "صدقة السر وفضلها"
    },
    {
      "text_id": 151126,
      "title": "نزهة الأسماع في مسألة السماع «أحكام الغناء والمعازف»"
    },
    {
      "text_id": 151127,
      "title": "سيرة عبد الملك بن عمر بن عبد العزيز"
    },
    {
      "text_id": 151128,
      "title": "تفسير سورة النصر"
    },
    {
      "text_id": 151129,
      "title": "تفسير سورة الإخلاص"
    },
    {
      "text_id": 151130,
      "title": "مقدمة تشتمل على أن جميع الرسل كان دينهم الإسلام"
    },
    {
      "text_id": 151131,
      "title": "القول الصواب في تزويج أمهات أولاد الغياب"
    },
    {
      "text_id": 151132,
      "title": "رسالة في رؤية هلال ذي الحجة"
    },
    {
      "text_id": 151133,
      "title": "قاعدة في إخراج الزكاة على الفور"
    },
    {
      "text_id": 151134,
      "title": "الرد على من اتبع غير المذاهب الأربعة"
    },
    {
      "text_id": 151135,
      "title": "مختصر في معاملة الظالم السارق"
    },
    {
      "text_id": 151136,
      "title": "أحكام الخواتيم"
    },
    {
      "text_id": 151137,
      "title": "شرح حديث «إن أغبط أوليائي»"
    },
    {
      "text_id": 151138,
      "title": "الكلام على قوله تعالى {إنما يخشى الله من عباده العلماء}"
    },
    {
      "text_id": 151140,
      "title": "فضل علم السلف على علم الخلف"
    },
    {
      "text_id": 151141,
      "title": "كلمة الإخلاص وتحقيق معناها - ضمن رسائل ابن رجب"
    },
    {
      "text_id": 151142,
      "title": "نور الاقتباس في مشكاة وصية النبي - صلى الله عليه وسلم - لابن عباس"
    },
    {
      "text_id": 151143,
      "title": "فضائل الشام"
    },
    {
      "text_id": 151144,
      "title": "استنشاق نسيم الأنس من نفحات رياض القدس"
    },
    {
      "text_id": 151146,
      "title": "اختيار الأولى في شرح حديث اختصام الملأ الأعلى - ضمن مجموع رسائل ابن رجب"
    },
    {
      "text_id": 151147,
      "title": "التخويف من النار والتعريف بحال دار البوار"
    },
    {
      "text_id": 151148,
      "title": "المحجة في سير الدلجة"
    },
    {
      "text_id": 1519,
      "title": "تسلية نفوس النساء والرجال عند فقد الأطفال"
    },
    {
      "text_id": 17894,
      "title": "قواعد ابن رجب - ت مشهور"
    },
    {
      "text_id": 200,
      "title": "أسباب المغفرة"
    },
    {
      "text_id": 21730,
      "title": "قواعد ابن رجب - ط الخانجي"
    },
    {
      "text_id": 22566,
      "title": "الفرق بين النصيحة والتعيير"
    },
    {
      "text_id": 22720,
      "title": "اختيار الأولى في شرح حديث اختصام الملأ الأعلى - ت الدوسري"
    },
    {
      "text_id": 26141,
      "title": "الحكم الجديرة بالإذاعة - ت الأرنؤوط"
    },
    {
      "text_id": 29574,
      "title": "تفسير سورة الفاتحة لابن رجب"
    },
    {
      "text_id": 30,
      "title": "قواعد ابن رجب - ط ركائز"
    },
    {
      "text_id": 31366,
      "title": "ذيل طبقات الحنابلة - لابن رجب - ت العثيمين"
    },
    {
      "text_id": 4033,
      "title": "التخويف من النار والتعريف بحال دار البوار"
    },
    {
      "text_id": 4268,
      "title": "جامع العلوم والحكم - ت الأرنؤوط"
    },
    {
      "text_id": 5767,
      "title": "شرح حديث لبيك اللهم لبيك"
    },
    {
      "text_id": 6238,
      "title": "الاستخراج لأحكام الخراج"
    },
    {
      "text_id": 6490,
      "title": "كلمة الإخلاص وتحقيق معناها - ط المكتب الإسلامي"
    },
    {
      "text_id": 667,
      "title": "أحكام الاختلاف في رؤية هلال ذي الحجة"
    },
    {
      "text_id": 949,
      "title": "جامع العلوم والحكم - ت الفحل"
    },
    {
      "text_id": 9552,
      "title": "شرح علل الترمذي"
    },
    {
      "text_id": 95735,
      "title": "مجموع رسائل ابن رجب"
    }
  ]
}