{
  "author_id": 2000,
  "author_meta": "ولد الدكتور محمد بكر إسماعيل فى المحاميد مركز أدفو بمحافظة أسوان عام ألف وتسعمائة وستة وثلاثين وحفظ القرآن الكريم فى سن مبكره\nالمؤهلات العلمية :\nحصل على الماجستير ثم الدكتوراة بدرجة امتياز مع مرتبه الشرف الأولى\nالماجستير في التفسير وعلوم القرآن الكريم بكلية أصول الدين ـ جامعة الأزهر.\nالدكتوراة في \" مقاصد التشريع الأسري من خلال سورتي الطلاق والتحريم\" .\nوتدرج فى سلك هيئه التدريس بجامعه الأزهر حتى وصل الى درجة أستاذ بكليه الدراسات الاسلامية\nوكان له باع كبير فى مجال الدعوة على مستوى مصر والعالم الاسلامى حيث عمل أستاذا بعدد من الجامعات العربية\nالمؤلفات :\nورغم أن تخصصه كان فى التفسير إلا أنه كان ذا ثقافه إسلاميه شاملة حيث أثرى المكتبة الاسلاميه بالعديد من الكتب والمؤلفات فى مجال الحديث والفقه والتاريخ الاسلامى واللغة والبلاغة وغيرها من فروع العلم ، وبلغت مولفاته أكثر من ثمانين مؤلفا من أبرزها :\n- الفقه الواضح على المذاهب الأربعة .\n- دراسات في علوم القرآن .\n- البيان في أحكام القرآن .\n- من وصايا الرسول ( صلى الله عليه وسلم )\n- خلاصة التفسير .\n- رجال أحبهم الرسول وبشرهم بالجنة .\n- نساء لهن شأن في الإسلام .\nو قد توفى الدكتور محمد بكر إسماعيل يرحمة الله ظهر يوم الخميس ثالث أيام عيد الأضحى المبارك وهو في الركعة الثانية من صلاة الظهر وهو ساجد، وكان ذلك في الحادى عشر من يناير من عام ٢٠٠٦",
  "books": [
    {
      "text_id": 10002,
      "title": "دراسات في علوم القرآن - محمد بكر إسماعيل"
    }
  ]
}