{
  "author_id": 2400,
  "author_meta": "القَلَانِسي (٤٣٥ - ٥٢١ هـ = ١٠٤٣ - ١١٢٧ م)\nمحمد بن الحسين بن بُندار، أبو العز القلانسي الواسطي\nمقرئ العراق في عصره. مولده ووفاته بواسط.\nمن كتبه\n(إرشاد المبتدي وتذكرة المنتهى - خ) في القراآت العشر [طُبع]\n(رسالة في القراآت الثلاث - خ)\n(الكفاية الكبرى - خ) في القراآت، أكبر من الأول [طُبع] (١).\n_________\n(١)  Brock ١: ٥١٩ (٤٠٨) S ١: ٧٢٣.  وغاية النهاية ٢: ١٢٨ والوافي بالوفيات ٣: ٤ والإعلام - خ\nنقلا عن: «الأعلام» للزركلي [مع إضافات بين معكوفين]",
  "books": [
    {
      "text_id": 1276,
      "title": "إرشاد المبتدي وتذكرة المنتهي في القراءات العشر - رسالة جامعية"
    },
    {
      "text_id": 1283,
      "title": "إرشاد المبتدي وتذكرة المنتهي في القراءات العشر - ط العلمية"
    }
  ]
}