{
  "author_id": 2601,
  "author_meta": "إلياس بن أحمد حسين - الشهير بالساعاتي - بن سليمان بن مقبول علي البرماوي.\nمن مواليد / مكة المكرمة، عام ١٣٨٦هـ، الموافق ١٩٦٧م.\n- درس المراحل الابتدائية إلى نهاية الصف الثاني في مدرسة الناصرية ثم إلى نهاية الصف الخامس، في مدرسة سلمان الفارسي؛ بمكة المكرمة، ثم انتقل إلى المدينة المنورة، وأكمل فيها المرحلة الإبتدائية والمتوسطة والثانوية، بمدارس العلوم الشرعية، بالمدينة المنورة.\n- حصل على شهادة البكالوريوس، في جامعة الإمام محمد بن سعود الإسلامية، فرع المدينة المنورة، عام ١٤١٢هـ.\n- حفظ القرآن الكريم، وتلقى القراءات العشر، والتجويد؛ على علماء وقراء الحرمين الشريفين، وغيرهما، وأجيز فيها، كما قرأ كتب القراءات والتجويد والتحريرات على شيوخه؛ وأجيز فيها.\n- كما قرأ كتب الحديث الشريف والمصطلح والنحو، وغيره على المختصين، وأجيز فيها بالسند المتصل، وتلقى العلوم الشرعية وغيرها، على علماء المدينة، وغيرها.\n- يقوم بتدريس القرآن الكريم والقراءات والتجويد، بالمسجد النبوي الشريف، وبجمعية تحفيظ القرآن الكريم، بالمدينة المنورة، منذ عام ١٤١٦هـ، وإلى الآن، كما يعمل بوظيفة موجه في الجمعية المذكورة.\n- كما يقوم بتدريس وإقراء وتصحيح قراءة مدرسي جمعية التحفيظ بمحافظة بدر، منذ شهر ربيع الأول، عام ١٤٣٠هـ.\n- كما اختير مدرسا لفصل المسابقات بجمعية التحفيظ بمنطقة حائل، من عام ١٤٣١هـ\n- قام بإمامة المصلين سنوات عديدة في بعض مساجد المدينة المنورة، كما قام بإمامة المصلين في صلاة التراويح، ولا يزال.\n- اختير عضواً في لجان التحكيم في المسابقات القرآنية التي تقيمها وزارة المعارف، في سنوات عديدة.\n- كما اختير مدرساً في المقرأة الصيفية التي تقيمها وزارة المعارف لتطوير وتحسين مدرسيها في مدارس القرآن الكريم الصباحية.\n- استفاد منه خلق كثير؛ قرؤوا عليه القرآن الكريم والقراءات، وكتب ومنظومات التجويد والقراءات والحديث الشريف واللغة وغيرها، وهم من داخل المملكة وخارجها، ومنهم طلاب المسابقات المحلية، والدولية التي تقيمها الدول العربية كل سنة.",
  "books": [
    {
      "text_id": 121374,
      "title": "إمتاع الفضلاء بتراجم القراء فيما بعد القرن الثامن الهجري"
    }
  ]
}