{
  "author_id": 2638,
  "author_meta": "مهندس مصري، ترك العمل بالهندسة وهو مهندس، ولكنه ترك العمل بهذا المجال وتفرغ للعلوم الشرعية\nمن الأفاضل خلقا وعلما - نحسبه على الخير، ولا نزكي على الله أحدا -.\nمن مشايخه:\nالشيخ مصطفى العدوي.\nالشيخ مجدي عرفات.\nالشيخ أحمد العيسوي.\nواستفاد من بعض مشايخ الكويت، والسعودية.\nله:\n- صحيح فقه السنة\n- فقه السنة للنساء.\n- كتاب في أحكام الجمعة.\n- كتاب في أخطاء النساء.\n- تحقيق كتاب تعظيم قدر الصلاة.\n- التعليق على شرح البيقونية للشيخ العثيمين.\n- التعليق على نزهة النظر.\nوغيرها",
  "books": [
    {
      "text_id": 13619,
      "title": "صحيح فقه السنة وأدلته وتوضيح مذاهب الأئمة"
    }
  ]
}