{
  "author_id": 2792,
  "author_meta": "القَنَازِعي (٣٤١ - ٤١٣ هـ = ٩٥٢ - ١٠٢٢ م)\nعبد الرحمن بن (مروان) بن عبد الرحمن الأنصاري، أبو المطرف القَنَازِعي\n[وورد اسم أبيه في بعض المخطوطات ومنها أجزاء من المدارك للقاضي عياض، في خزانة الرباط وعند الفقيه التطواني في سلا، بلفظ (هرون) إلا أن لوحة خطه قطعت الشك بأنه (مروان).]\nفقيه، مالكي، من رجال الحديث والتفسير. من أهل قرطبة. رحل إلى المشرق سنة ٣٦٧ هـ وعاد سنة ٣٧١ والقنازعي نسبة إلى عمل (القنازع) وكان يصنعها، ويرجح أنها صناعة القلانس (انظر دوزي ٢: ٤١١)\nله كتب، منها\n(شرح الموطأ)\n(عقد الشروط وعللها)\n(اختصار تفسير ابن سلام)\nنقلا عن: «الأعلام» للزركلي",
  "books": [
    {
      "text_id": 16787,
      "title": "تفسير الموطأ للقنازعي"
    }
  ]
}