{
  "author_id": 2850,
  "author_meta": "شَيْخ زَادَهْ (٠٠٠ - ٩٥١ هـ = ٠٠٠ - ١٥٤٤ م)\nمحمد (محيي الدين) بن مصطفى (مصلح الدين) القُوجَوي: مفسر، من فقهاء الحنفية. كان مدرسا في إستانبول.\nله:\n(حاشية على أنوار التنزيل للبيضاوي - ط) أربعة مجلدات، قال الحاج خليفة: وهي أعظم الحواشي فائدة وأكثرها نفعا وأسهلها عبارة\n(شرح الوقاية) في الفقه\n(شرح الفرائض السراجية)\n(شرح المفتاح للسكاكي\n(شرح البردة - خ)\n(حاشية على مشارق الأنوار للصاغاني - خ) في إسطنبول (١).\n_________\n(١) كشف الظنون ١: ١٨٨ وفيه: وفاته سنة ٩٥١ وعنه التيمورية ١: ٢٧ ثم ٣: ١٧٠ وفي الشقائق النعمانية ١: ٤٥٦ (مات سنة ٩٥٠) وعنه شذرات ٨: ٢٨٦ وسماه صاحب الشقائق (محمد ابن شيخ مصلح الدين) وهو في الشذرات (محمد بن مصطفى) وفي التيمورية: (ورد اسمه في آخر المجلد الثالث من حاشيته على البيضاوي: محمد محيي الدين). ووقعت لي نسخة من كتابه (شرح البردة) وفي آخرها: (قد صاغ هذا الشرح اللطيف على البردة العالم الرباني مصلح الدين محمد بن مصطفى بن شمس الدين الشهير بشيخ زاده). وطوبقبو ٢: ٢٠٩ ودار الكتب ٣: ١٥٦.\nنقلا عن: «الأعلام» للزركلي",
  "books": [
    {
      "text_id": 19236,
      "title": "شرح قواعد الإعراب"
    }
  ]
}