{
  "author_id": 578,
  "author_meta": "ابن أبي عمر (٥٩٧ - ٦٨٢ هـ = ١٢٠٠ - ١٢٨٣ م)\nعبد الرحمن [ابن الشيخ أبي عُمَر] محمد بن أحمد بن قدامة المقدسي الجماعيلي الحنبلي، أبو الفرج، شمس الدين:\nفقيه، من أعيان الحنابلة.\nولد وتوفي في دمشق. وهو أول من ولي قضاء الحنابلة بها، استمر فيه نحو ١٢ عاما ولم يتناول عليه (معلوما) ثم عزل نفسه.\nله تصانيف، منها: (الشافي - ط) وهو الشرح الكبير للمقنع في فقه الحنابلة (١).\n_________\n(١) المقصد الأرشد - خ. والنجوم الزاهرة ٧: ٣٥٨ وفوات الوفيات ١: ٢٦٢ والذيل على طبقات الحنابلة، طبعة الفقي ٢: ٣٠٤.\nنقلا عن: «الأعلام» للزركلي [مع إضافة يسيرة بين معقوفين]",
  "books": [
    {
      "text_id": 1153,
      "title": "الشرح الكبير على المقنع - ط المنار"
    },
    {
      "text_id": 19188,
      "title": "الشرح الكبير على المقنع - ت التركي"
    }
  ]
}