{
  "author_id": 60,
  "author_meta": "أبو الحسن التبريزي (٦٧٧ - ٧٤٦ هـ = ١٢٧٨ - ١٣٤٥ م)\nعلي بن عبد الله بن [الحسين] (١) الأرْدَبيلي التِّبْريزي، أبو الحسن تاج الدين\nباحث، من علماء الشافعية.\nولد في أردبيل (بأذربيجان) وسكن تبريز. ورحل إلى بغداد، فمكة حاجا، فمصر\nوأفتى وهو ابن ثلاثين سنة. وأصم في آخر عمره. ومات بالقاهرة.\n(له)\n«مبسوط الأحكام - خ» في دار الكتب\nوكتب في «التفسير» و «الحديث» و «الأصول» و «الحساب» منها:\n«الكافي في علوم الحديث - خ» في استامبول [طُبع]\nو «القسطاس المستقيم في الحديث الصحيح القويم - خ» أيضا (٢).\n_________\n(١) بالأعلام: «الحسن». قال مشهور آل سلمان (في مقدمة تحقيق «الكافي في علوم الحديث»): وعند ابن قاضي شهبة في «تاريخه» وتبعه الزِّركلي: «علي بن عبد الله بن الحُسين»! وصوابه «ابن الحسن». ا هـ\nوهي كذلك «ابن الحسن» في صورة مخطوط بخط المترجم أوردها الزركلي نفسه في ترجمته، وأوردها أيضا مشهور في مقدمة تحقيقه للكافي\n(٢) الدرر الكامنة ٣: ٧٢ وعلماء بغداد ١٤٦ ومعجم الأطباء ٣٠٧ ودار الكتب ٢: ١٥٦ وطوبقبو ٢: ٥، ٢٢٨.\nنقلا عن: «الأعلام» للزركلي [مع إضافات بين معكوفين]",
  "books": [
    {
      "text_id": 789,
      "title": "الكافي في علوم الحديث"
    }
  ]
}