{
  "author_id": 620,
  "author_meta": "علي بن محمد الخزاعي (٧١٠ - ٧٨٩ هـ = ١٣١٠ - ١٣٨٧ م)\nعلي بن محمد بن أحمد بن موسى ابن مسعود، أبو الحسن ابن ذي الوزارتين، الخزاعي: بحاثة مؤرخ أديب، أندلسي الأصل. مولده بتلمسان، ووفاته بفاس.\nاستكتبه السلطان إبراهيم المريني. ثم كتب في ديوان بني زيان بتلمسان. واستقر أخيرا في بلاط بني مرين.\nوصنف للسلطان المتوكل على الله أبي فارس المريني (سنة ٧٨٦ هـ) كتابه «تخريج الدلالات السمعية، على ما كان في عهد رسول الله صلى الله عليه وسلم من الحرف والصنائع والعمالات الشرعية - خ» [ثم طُبع] اطلع عبد الحي الكتاني على نسخة منه غير تامة، فأضاف إليها زيادات كثيرة ونسب الكتاب كله إليه، وسماه «التراتيب الإدارية - ط» في مجلدين، وعلمت أن ما فات الكتاني من كتاب الخزاعي هو نحو ربعه ثم رأيت هذا الربع في إحدى خزائن تطوان الخاصة ونقلت عنه خزانة الرباط نسخة بالتوصير الشمسي .\nنقلا عن : الأعلام للزركلي",
  "books": [
    {
      "text_id": 9790,
      "title": "تخريج الدلالات السمعية"
    }
  ]
}