{
  "author_id": 671,
  "author_meta": "العَيْدَرُوس (٩٧٨ - ١٠٣٨ هـ = ١٥٧٠ - ١٦٢٨ م)\nعبد القادر بن شيخ بن عبد الله بن شيخ بن عبد الله العَيْدَرُوس: مؤرخ باحث، من أهل اليمن.\nسكن حضرموت وانتقل إلى أحمد اباد (بالهند) فتوفي فيها. من كتبه «النور السافر عن أخبار القرن العاشر - ط» و «الروض الناضر في من اسمه عبد القادر من أهل القرنين التاسع والعاشر - خ» و «تعريف الأحياء بفضائل الإحياء - ط» و «الفتوحات القدسية في الخرقة العيدروسية» و «الحدائق الخضرة في سيرة النبي وأصحابه العشرة» و «الحضرة العزيزة بعيون السير الوجيزة» و «الأنموذج» في مناقب أهل بدر، و «الدر الثمين في بيان المهمّ من علم الدين» و «غاية القرب في شرح نهاية الطلب» و «الروض الأريض» وهو مجموع منظوماته، و «قرة العين في مناقب الولي باحسين» و «الزهر الباسم من روض الأستاذ حاتم - خ» ٣٦ ورقة في مكتبة البار، بالقرين (اليمن)\nنقلا عن : الأعلام للزركلي",
  "books": [
    {
      "text_id": 6676,
      "title": "النور السافر عن أخبار القرن العاشر"
    }
  ]
}