{
  "author_id": 719,
  "author_meta": "ابن حمزة الحسيني (٧١٥ - ٧٦٥ هـ = ١٣١٥ - ١٣٦٤ م)\nمحمد بن علي بن الحسن بن حمزة الحسيني الدمشقي، شمس الدين، أبو المحاسن: حافظ للحديث، مؤرخ.\nمولده ووفاته في دمشق.\nكان شاهد المواريث فيها، وولي مشيخة دار الحديث البهائية.\nمن كتبه (عبر الأعصار وخبر الأمصار) بلغ فيه شعبان سنة ٧٦٥ (قبيل وفاته) و (الكشاف في معرفة الأطراف - خ) في الحديث، و (ذيل تذكرة الحفاظ للذهبي - ط) و (ذيل العبر للذهبي - خ) و (التذكرة في رجال العشرة - خ) و (العرف الذكي في النسب الزكي) و (معجم شيوخه) و (تعليق على الميزان) بين فيه كثيرا من الأوهام واستدرك عليه عدة أسماء، و (الإلمام بآداب دخول الحمام - خ) رسالة، و (الإكمال - خ) في ذكر من له رواية في مسند الإمام أحمد بن حنبل، و (اختصار تهذيب الكمال - خ) المجلد الثاني منه، رأيته بخطه، حذف من الأصل من ليس في الكتب الستة، وأضاف إليه من في مسند أحمد والموطأ ومسند الشافعي ومسند أبي حنيفة\nنقلا عن : الأعلام للزركلي",
  "books": [
    {
      "text_id": 5850,
      "title": "الإكمال في ذكر من له رواية في مسند الإمام أحمد من الرجال"
    },
    {
      "text_id": 7307,
      "title": "ذيل تذكرة الحفاظ للحسيني"
    }
  ]
}