{
  "author_id": 742,
  "author_meta": "النعيمي (٨٤٥ - ٩٢٧ هـ = ١٤٤٢ - ١٥٢١ م)\nعبد القادر بن محمد النعيمي الدمشقي، ولد في دمشق سنة ٨٤٥ هـ، وكان شديد الحب بمسقط رأسه الذي تولى فيه ولفترة منصب القضاء. وهو من أشهر من كتب في فضائل دمشق ولكنه ليس بآخرهم. تتلمذ على يديه ابن طولولن. وهو قد تتلمذ على يد العديد من الشيوخ أمثال إبراهيم الناجي، وزين الدين عبد الرحمن بن خليل، وزين الدين خطاب الغزاوي، وزين الدين مفلح بن عبد الله الحبشي المصري ثم الدمشقي وتجلبب على يد شيخه الأخير جلباب التصوف. كما وأفاد من بدر بن القاضي شهبة وشهاب بن قراء وقرأ كتابه« الإيذان» على برهان البقاعي وتسلم منه إجازة الرواية.\nآثاره\nخلّف آثاراً كثيرة أمثال: الدارس في تاريخ المدارس، تذكرة الإخوان في حوادث الزمان، التبيين في تراجم العلماء والصالحين، العنوان في ضبط مواليد ووفيات أهل الزمان، القول المبين المحكم في إهداء القرب للنبي( صلى الله عليه وسلم)، تحفة البررة في الأحاديث المعتبرة، إفادة النقل في الكلام على العقل وغيره.\nتوفي النعيمي في سنة ٩٧٨ هـ.\nوجاء في الأعلام للزركلي، ما يلي:\nعبد القادر بن محمد بن عمر بن محمد ابن يوسف بن عبد الله بن نعيم، أبو المفاخر: مؤرخ دمشق في عصره.\nمن علماء الحديث ، مولده ووفاته في دمشق.\nمن كتبه «الدارس في تاريخ المدارس - ط» مجلدان و «العنوان، في ضبط المواليد والوفيات لأهل الزمان - خ» و «تذكرة الإخوان في حوادث الزمان» و «التبيين في تراجم العلماء والصالحين» و «تحفة البررة في الأحاديث المعتبرة» و «إفادة النقل في الكلام على العقل»",
  "books": [
    {
      "text_id": 8880,
      "title": "الدارس في تاريخ المدارس"
    }
  ]
}