{
  "author_id": 761,
  "author_meta": "ابن جابر البتاني ( ٠٠٠ - ٣١٧ هـ = ٠٠٠ - ٩٢٩ م)\nمحمد بن جابر بن سنان الحراني الرقي الصابئ، أبو عبد الله المعروف بالبتاني (١) : فلكي مهندس، يسميه الفرنج  Albategni أو Albatenius ولد قبل سنة ٢٤٤ هـ (٨٥٨ م) وكان من أهل (حران) وسكن (الرقة) واشتغل برصد الكواكب من سنة ٢٦٤ إلى ٣٠٦ هـ. ورحل مع بعض أهل الرقة إلى بغداد، في ظلامات لهم، فلما رجع مات في طريقه بقصر الجص، قرب سامراء.\nوهو صاحب (الزيج - ط) المعروف بزيج الصابئ، ثلاثة أجزاء، وطبعت ترجمته إلى اللاتينية في نور مبرج سنة ١٥٣٧ م باسم Scientia Stellarum وقالوا إنه أصح من زيج بطليموس.\nومن كتبه (معرفة مطالع البروج فيما بين أرباع الفلك) و (شرح أربع مقالات لبطليموس) ورسالة في (تحقيق أقدار الاتصالات)\nولم يعلم أحد في الإسلام بلغ مبلغ ابن جابر في تصحيح أرصاد الكواكب وامتحان حركاتها.\nوكان يرصد في الرقة على الضفة اليسرى من الفرات.\nوهو - كما يقول محمد مسعود - أول من كشف السمت Azimuth والنظير Nadir وحدد نقطتيهما من السماء.\nوالكلمتان عند علماء الفلك الإفرنج، عربيتان.\nواكتشف حركة الأوج الشمسي وتقدم المدار الشمسي وانحرافه، والجيب الهندسي والأوتار (٢) ويقول المستشرق (نلينو) إن له رصودا جليلة للكسوف والخسوف اعتمد عليها دنتورن Dunthorne سنة ١٧٤٩ في تحديد تسارع القمر في حركته خلال قرن من الزمان.\nوقال لالند (٣) Lalande الفلكي الفرنسي: (البتاني أحد الفلكيين العشرين الأئمة الذين ظهروا في العالم كله)\nـــــــــــــ\n(١) في ابن الوردي: البتاني، بفتح الموحدة وقد تكسر وفي ابن خلكان بمعناه. وقال ياقوت: بتان - بالفتح - من نواحي حران، ينسب إليها البتاني، ذكره ابن الأكفاني بكسر الباء.\n(٢) قاله تشمبرلس في موسوعات العلوم الفلكية الانجليزية.\n(٣) مجلة المقتطف ١: ١٨ والقفطي ٨٤ والوفيات ٢: ٨٠ و ٣١ Gregoire ونواح مجيدة من الثقافة الإسلامية ٥٤ وابن الوردي ١: ٢٦١ ونلينو.C.A Nallino في دائرة المعارف الاسلامية ٣: ٣٣٦ ومحمد مسعود، في التعليق على هامشها. وعلم الفلك، لنلينو: انظر فهرسته. والفهرست لابن النديم: الفن الثاني من المقالة السابعة. وانظر ٢٥٢: ١. Brock ٣٩٧: ١.\nنقلا عن : الأعلام للزركلي",
  "books": [
    {
      "text_id": 452,
      "title": "زيج الصابئ"
    }
  ]
}