{
  "author_id": 786,
  "author_meta": "أبو الفضل الميداني (٠٠٠ - ٥١٨ هـ = ٠٠٠ - ١١٢٤ م)\nأحمد بن محمد بن أحمد بن إبراهيم الميداني النيسابوري، أبو الفضل: الأديب البحاث، صاحب (مجمع الأمثال - ط) لم يؤلف مثله في موضوعه.\nولد الميداني ونشأ وتوفي في نيسابور (حاضرة خراسان) ونسبته إلى (ميدان زياد) محلة فيها.\nومن كتبه (نزهة الطرف في علم الصرف - ط) و (السامي في الأسامي - ط) في اللغة، و (الهادي للشادي - خ) نحو،\nو (شرح المفضليات)\nنقلا عن : الأعلام للزركلي",
  "books": [
    {
      "text_id": 12929,
      "title": "مجمع الأمثال"
    }
  ]
}