{
  "author_id": 813,
  "author_meta": "ابن حبيب الحلبي (٧١٠ - ٧٧٩ هـ = ١٣١٠ - ١٣٧٧ م)\nالحسن بن عمر بن الحسن بن حبيب، أبو محمد، بدر الدين الحلبي: مؤرخ، من الكتاب المترسلين.\nولد في دمشق، ونصب أبوه محتسبا في حلب فانتقل معه، فنشأ فيها، ونسب إليها.\nثم رحل إلى مصر والحجاز، وعاد. وتنقل في بلاد الشام واستقر في حلب.\nله (نسيم الصبا - ط) صغير، و (درة الأسلاك في دولة الأتراك - ط) أرخ به أخبارهم من سنة ٦٤٨ - ٧٧٨ هـ، وجهينة الأخبار في أسماء الخلفاء وملوك الأمصار - خ) و (تذكرة النبيه في أيام المنصور وبنيه - خ) جمع به أخبار السلطان قلاوون وأبنائه، و (النجم الثاقب - ط) في السيرة النبوية و (المقتفى في ذكر فضائل المصطفى - خ) و (كشف المروط - خ) في فقه الشافعية.\nنقلا عن : الأعلام للزركلي",
  "books": [
    {
      "text_id": 575,
      "title": "نسيم الصبا"
    },
    {
      "text_id": 6582,
      "title": "المقتفى من سيرة المصطفى"
    }
  ]
}